PHASE7_ALERTING.py
PHASE7_ERROR_HANDLING.py
PHASE7_MONITORING.py
PHASE7_SECURITY.py
universcell_framework-1.0.0.dist-info/licenses/LICENSE
universcell_framework-1.0.0.dist-info/METADATA
universcell_framework-1.0.0.dist-info/WHEEL
universcell_framework-1.0.0.dist-info/top_level.txt
universcell_framework-1.0.0.dist-info/RECORD
