Metadata-Version: 2.4
Name: universcell-framework
Version: 1.0.0
Summary: Enterprise governance framework with 7 adoption patterns
Home-page: https://github.com/universcell/framework
Author: Universell Framework Team
Author-email: framework@universcell.io
License: MIT
Project-URL: Bug Tracker, https://github.com/universcell/framework/issues
Project-URL: Documentation, https://framework.universcell.io
Project-URL: Source Code, https://github.com/universcell/framework
Keywords: framework,governance,kubernetes,ci-cd,database,finance,error-handling,monitoring,security,alerting
Classifier: Development Status :: 5 - Production/Stable
Classifier: Intended Audience :: Developers
Classifier: Intended Audience :: System Administrators
Classifier: License :: OSI Approved :: MIT License
Classifier: Programming Language :: Python :: 3
Classifier: Programming Language :: Python :: 3.8
Classifier: Programming Language :: Python :: 3.9
Classifier: Programming Language :: Python :: 3.10
Classifier: Programming Language :: Python :: 3.11
Classifier: Programming Language :: Python :: 3.12
Classifier: Operating System :: OS Independent
Classifier: Topic :: System :: Monitoring
Classifier: Topic :: System :: Networking
Classifier: Topic :: System :: Systems Administration
Requires-Python: >=3.8
License-File: LICENSE
Requires-Dist: dataclasses-json>=0.5.7
Dynamic: author
Dynamic: author-email
Dynamic: classifier
Dynamic: description
Dynamic: description-content-type
Dynamic: home-page
Dynamic: keywords
Dynamic: license
Dynamic: license-file
Dynamic: project-url
Dynamic: requires-dist
Dynamic: requires-python
Dynamic: summary
